LICENSE
MANIFEST.in
Pipfile
Pipfile.lock
README.md
pyproject.toml
setup.py
test_helloworld.py
tox.ini
src/helloworld.py
src/helloworld_msusol.egg-info/PKG-INFO
src/helloworld_msusol.egg-info/SOURCES.txt
src/helloworld_msusol.egg-info/dependency_links.txt
src/helloworld_msusol.egg-info/requires.txt
src/helloworld_msusol.egg-info/top_level.txt