Metadata-Version: 2.1
Name: helloworld-msusol
Version: 0.0.2
Summary: Say hello!
Home-page: https://github.com/msusol/helloworld
Author: Mark Susol
Author-email: marksusol@gmail.com
License: UNKNOWN
Platform: UNKNOWN
Classifier: Programming Language :: Python :: 3
Classifier: Programming Language :: Python :: 3.7
Classifier: Programming Language :: Python :: 3.9
Classifier: License :: OSI Approved :: GNU General Public License v2 or later (GPLv2+)
Classifier: Operating System :: OS Independent
Provides-Extra: dev
